pylsd/__init__.py
pylsd/lsd.py
pylsd/bindings/__init__.py
pylsd/bindings/lsd_ctypes.py
pylsd/lib/darwin/liblsd.dylib
pylsd/lib/linux/liblsd.so
pylsd/lib/win32/x64/lsd.dll
pylsd_nova-1.0.0.dist-info/LICENSE
pylsd_nova-1.0.0.dist-info/METADATA
pylsd_nova-1.0.0.dist-info/WHEEL
pylsd_nova-1.0.0.dist-info/top_level.txt
pylsd_nova-1.0.0.dist-info/RECORD
