Metadata-Version: 2.1
Name: pylsd-nova
Version: 1.0.0
Summary: pylsd-nova is a python binding for LSD - Line Segment Detector
Home-page: https://github.com/AndranikSargsyan/pylsd-nova
Author: Andranik Sargsyan
Author-email: and.sargsyan@yahoo.com
License: BSD
Keywords: LSD
Platform: UNKNOWN
